quicktest/__init__.py
quicktest/printer.py
quicktest/quicktest.py
quicktest/summary.py
quicktest/tester.py
quicktest/util.py
quicktest-0.1.3.dist-info/DESCRIPTION.rst
quicktest-0.1.3.dist-info/METADATA
quicktest-0.1.3.dist-info/RECORD
quicktest-0.1.3.dist-info/WHEEL
quicktest-0.1.3.dist-info/metadata.json
quicktest-0.1.3.dist-info/top_level.txt
